STMint/STMint.py
STMint/TensorNormUtilities.py
STMint/__init__.py
STMint-1.2.1.dist-info/LICENSE
STMint-1.2.1.dist-info/METADATA
STMint-1.2.1.dist-info/WHEEL
STMint-1.2.1.dist-info/top_level.txt
STMint-1.2.1.dist-info/RECORD
