Metadata-Version: 2.1
Name: STMint
Version: 1.2.1
Summary: State Transition Matrix Integrator
Home-page: https://github.com/SIOSlab/STMInt
Author: Jackson Kulik, Cedric Orton-Urbina
Author-email: cpk258@cornell.edu, ceo29@cornell.edu
License: MIT
Classifier: Programming Language :: Python :: 3.10
Classifier: Programming Language :: Python :: 3.11
Classifier: Programming Language :: Python :: 3.12
Classifier: License :: OSI Approved :: BSD License
Classifier: Operating System :: OS Independent
Requires-Python: >=3.9
License-File: LICENSE
Requires-Dist: numpy
Requires-Dist: scipy
Requires-Dist: astropy
Requires-Dist: sympy<1.13
